sideload_caddy_2_bin_6633ee68e41b4d34e4ede1ee/__init__.py
sideload_caddy_2_bin_6633ee68e41b4d34e4ede1ee/caddy_2.7.6_windows_armv7.sbom.sig
sideload_caddy_2_bin_6633ee68e41b4d34e4ede1ee-1.0.0.dist-info/METADATA
sideload_caddy_2_bin_6633ee68e41b4d34e4ede1ee-1.0.0.dist-info/WHEEL
sideload_caddy_2_bin_6633ee68e41b4d34e4ede1ee-1.0.0.dist-info/top_level.txt
sideload_caddy_2_bin_6633ee68e41b4d34e4ede1ee-1.0.0.dist-info/RECORD
