Metadata-Version: 2.1
Name: sideload_caddy_2_bin_6633ee68e41b4d34e4ede1ee
Version: 1.0.0
Summary: Sideloaded package
Author: Null Void
Requires-Python: >=3.8
